codex/__init__.py
codex/applications/__init__.py
codex/applications/lifespan.py
codex/applications/websocket.py
codex/asgi.py
codex/authentication.py
codex/choices/__init__.py
codex/choices/admin.py
codex/choices/browser.py
codex/choices/choices_to_json.py
codex/choices/notifications.py
codex/choices/reader.py
codex/choices/search.py
codex/choices/statii.py
codex/librarian/__init__.py
codex/librarian/bookmark/__init__.py
codex/librarian/bookmark/bookmarkd.py
codex/librarian/bookmark/latest_version.py
codex/librarian/bookmark/tasks.py
codex/librarian/bookmark/update.py
codex/librarian/bookmark/user_active.py
codex/librarian/covers/__init__.py
codex/librarian/covers/coverd.py
codex/librarian/covers/create.py
codex/librarian/covers/path.py
codex/librarian/covers/purge.py
codex/librarian/covers/status.py
codex/librarian/covers/tasks.py
codex/librarian/cron/__init__.py
codex/librarian/cron/crond.py
codex/librarian/librariand.py
codex/librarian/memory.py
codex/librarian/mp_queue.py
codex/librarian/notifier/__init__.py
codex/librarian/notifier/notifierd.py
codex/librarian/notifier/tasks.py
codex/librarian/restarter/__init__.py
codex/librarian/restarter/restarter.py
codex/librarian/restarter/status.py
codex/librarian/restarter/tasks.py
codex/librarian/scribe/__init__.py
codex/librarian/scribe/importer/__init__.py
codex/librarian/scribe/importer/const.py
codex/librarian/scribe/importer/create/__init__.py
codex/librarian/scribe/importer/create/comics.py
codex/librarian/scribe/importer/create/const.py
codex/librarian/scribe/importer/create/covers.py
codex/librarian/scribe/importer/create/folders.py
codex/librarian/scribe/importer/create/foreign_keys.py
codex/librarian/scribe/importer/create/link_fks.py
codex/librarian/scribe/importer/delete/__init__.py
codex/librarian/scribe/importer/delete/comics.py
codex/librarian/scribe/importer/delete/covers.py
codex/librarian/scribe/importer/delete/folders.py
codex/librarian/scribe/importer/failed/__init__.py
codex-1.9.15.dist-info/WHEEL
codex-1.9.15.dist-info/entry_points.txt
codex-1.9.15.dist-info/METADATA
codex-1.9.15.dist-info/RECORD
