Metadata-Version: 2.4
Name: codex
Version: 1.9.15
Summary: A comic archive web server.
Keywords: comic,cbz,cbr,cb7,cbt,pdf
Author: AJ Slater
Author-email: AJ Slater <aj@slater.net>
License-Expression: GPL-3.0-only
Classifier: Development Status :: 5 - Production/Stable
Classifier: Environment :: Web Environment
Classifier: Framework :: Django :: 5.1
Classifier: Intended Audience :: End Users/Desktop
Classifier: License :: OSI Approved :: GNU General Public License v3 (GPLv3)
Classifier: Natural Language :: English
Classifier: Operating System :: OS Independent
Classifier: Programming Language :: JavaScript
Classifier: Programming Language :: Python :: 3 :: Only
Classifier: Topic :: Internet :: WWW/HTTP
Classifier: Topic :: Multimedia :: Graphics :: Viewers
Requires-Dist: aioprocessing~=2.0
Requires-Dist: ansicolors~=1.1
Requires-Dist: bidict~=0.23
Requires-Dist: channels~=4.2
Requires-Dist: comicbox[pdf]~=2.1.1
Requires-Dist: dateparser~=1.2
Requires-Dist: django~=5.2
Requires-Dist: djangorestframework~=3.16
Requires-Dist: djangorestframework-camel-case~=1.4
Requires-Dist: django-cachalot~=2.8
Requires-Dist: django-cors-headers~=4.0
Requires-Dist: django-rest-registration~=0.9
Requires-Dist: django-vite~=3.1
Requires-Dist: drf-spectacular~=0.28
Requires-Dist: fnvhash~=0.1
Requires-Dist: humanfriendly~=10.0
Requires-Dist: humanize~=4.12
Requires-Dist: hypercorn[h3]~=0.17
Requires-Dist: nh3~=0.2
Requires-Dist: psutil~=7.1
Requires-Dist: pyparsing~=3.2
Requires-Dist: requests~=2.24
Requires-Dist: typing-extensions~=4.14
Requires-Dist: tzlocal~=5.0
Requires-Dist: watchdog~=6.0
Requires-Dist: websocket-client~=1.2
Requires-Dist: whitenoise[brotli]~=6.0
Requires-Dist: versio~=0.5
Requires-Dist: zipstream-ng~=1.8
Requires-Dist: pillow~=12.0
Requires-Dist: loguru~=0.7.3
Requires-Python: >=3.10
Project-URL: Demo, https://demo.codex-reader.app/
Project-URL: Docker Image, https://hub.docker.com/r/ajslater/codex
Project-URL: Documentation, https://codex-comic-reader.readthedocs.io
Project-URL: Issues, https://github.com/ajslater/codex/issues
Project-URL: News, https://codex-comic-reader.readthedocs.io/NEWS/
Project-URL: Source, https://github.com/ajslater/codex
